<?xml version="1.0" encoding="UTF-8"?>
<templates xml:space="preserve">

    <t t-name="vnop_sync.ExportMatTemplateMenu">
        <DropdownItem class="'o_vnop_export_template_mat'" onSelected.bind="onSelected">
            <i class="fa fa-fw fa-download me-1"/>Xuất mẫu Mắt kính
        </DropdownItem>
    </t>

    <t t-name="vnop_sync.ExportGongTemplateMenu">
        <DropdownItem class="'o_vnop_export_template_gong'" onSelected.bind="onSelected">
            <i class="fa fa-fw fa-download me-1"/>Xuất mẫu Gọng kính
        </DropdownItem>
    </t>

    <t t-name="vnop_sync.ExportPhuKienTemplateMenu">
        <DropdownItem class="'o_vnop_export_template_phukien'" onSelected.bind="onSelected">
            <i class="fa fa-fw fa-download me-1"/>Xuất mẫu Phụ kiện
        </DropdownItem>
    </t>

</templates>
